{
  "fusion": "github.com-danielgonzagat-dojo.jl",
  "plan": {
    "source_url": "https://github.com/danielgonzagat/Dojo.jl",
    "mode": "auto"
  },
  "genes": {
    "source_url": "https://github.com/danielgonzagat/Dojo.jl",
    "reachable": true
  },
  "adapter": {
    "engine": "NeuroEvoHybrid",
    "population": 8,
    "generations": 1,
    "model": "distilbert-base-uncased"
  },
  "metrics": {
    "caos_pre": 0.7975835740559978,
    "caos_pos": 0.8127882596783096,
    "delta_linf": 0.0032394544794606094,
    "sr": 0.86495395827578,
    "G": 0.866026928243361,
    "ece": 0.011355416277833536,
    "rho_bias": 1.013210040678969,
    "fp": 0.023021363687457212
  },
  "gate_pass": true,
  "timestamp": 1759361265.306123,
  "_slug": "github.com-danielgonzagat-dojo.jl"
}