{
  "fusion": "github.com-danielgonzagat-typia",
  "plan": {
    "source_url": "https://github.com/danielgonzagat/typia",
    "mode": "auto"
  },
  "genes": {
    "source_url": "https://github.com/danielgonzagat/typia",
    "reachable": true
  },
  "adapter": {
    "engine": "NeuroEvoHybrid",
    "population": 8,
    "generations": 1,
    "model": "distilbert-base-uncased"
  },
  "metrics": {
    "caos_pre": 0.7975835740559978,
    "caos_pos": 0.8127862802120808,
    "delta_linf": 0.0032419113678521343,
    "sr": 0.86530354895212,
    "G": 0.8659302857271942,
    "ece": 0.01134970387267775,
    "rho_bias": 1.0129001322848232,
    "fp": 0.023023942104442943
  },
  "gate_pass": true,
  "timestamp": 1759362205.1432478,
  "_slug": "github.com-danielgonzagat-typia"
}