{
  "fusion": "github.com-danielgonzagat-openvino",
  "plan": {
    "source_url": "https://github.com/danielgonzagat/openvino",
    "mode": "auto"
  },
  "genes": {
    "source_url": "https://github.com/danielgonzagat/openvino",
    "reachable": true
  },
  "adapter": {
    "engine": "NeuroEvoHybrid",
    "population": 8,
    "generations": 1,
    "model": "distilbert-base-uncased"
  },
  "metrics": {
    "caos_pre": 0.7975835740559978,
    "caos_pos": 0.8128054297977099,
    "delta_linf": 0.003240276504815985,
    "sr": 0.8654839409026398,
    "G": 0.8657289355247976,
    "ece": 0.011347726017691377,
    "rho_bias": 1.0137149806497643,
    "fp": 0.023029874598241035
  },
  "gate_pass": true,
  "timestamp": 1759368510.343085,
  "_slug": "github.com-danielgonzagat-openvino"
}