{
  "fusion": "github.com-danielgonzagat-weaviate",
  "plan": {
    "source_url": "https://github.com/danielgonzagat/weaviate",
    "mode": "auto"
  },
  "genes": {
    "source_url": "https://github.com/danielgonzagat/weaviate",
    "reachable": true
  },
  "adapter": {
    "engine": "NeuroEvoHybrid",
    "population": 8,
    "generations": 1,
    "model": "distilbert-base-uncased"
  },
  "metrics": {
    "caos_pre": 0.7975835740559978,
    "caos_pos": 0.8130462790543388,
    "delta_linf": 0.003241279916023136,
    "sr": 0.8656463525833207,
    "G": 0.8659597554048676,
    "ece": 0.011348229360725846,
    "rho_bias": 1.013141508084813,
    "fp": 0.02303304477476933
  },
  "gate_pass": true,
  "timestamp": 1759379241.016264,
  "_slug": "github.com-danielgonzagat-weaviate"
}