{
  "fusion": "github.com-danielgonzagat-did-verification-consensus-protocol",
  "plan": {
    "source_url": "https://github.com/danielgonzagat/did-verification-consensus-protocol",
    "mode": "auto"
  },
  "genes": {
    "source_url": "https://github.com/danielgonzagat/did-verification-consensus-protocol",
    "reachable": true
  },
  "adapter": {
    "engine": "NeuroEvoHybrid",
    "population": 8,
    "generations": 1,
    "model": "distilbert-base-uncased"
  },
  "metrics": {
    "caos_pre": 0.7975835740559978,
    "caos_pos": 0.8129422231878809,
    "delta_linf": 0.003240678781755846,
    "sr": 0.8653521750807509,
    "G": 0.8660027972543209,
    "ece": 0.011355821707943442,
    "rho_bias": 1.0129750043123407,
    "fp": 0.02301876980268143
  },
  "gate_pass": true,
  "timestamp": 1759355251.9721758,
  "_slug": "github.com-danielgonzagat-did-verification-consensus-protocol"
}