{
  "fusion": "github.com-danielgonzagat-aequitas",
  "plan": {
    "source_url": "https://github.com/danielgonzagat/aequitas",
    "mode": "auto"
  },
  "genes": {
    "source_url": "https://github.com/danielgonzagat/aequitas",
    "reachable": true
  },
  "adapter": {
    "engine": "NeuroEvoHybrid",
    "population": 8,
    "generations": 1,
    "model": "distilbert-base-uncased"
  },
  "metrics": {
    "caos_pre": 0.7975835740559978,
    "caos_pos": 0.8130997771203233,
    "delta_linf": 0.003240782275261407,
    "sr": 0.8649714388944334,
    "G": 0.8659476681119225,
    "ece": 0.01135302779610119,
    "rho_bias": 1.0138297442260362,
    "fp": 0.023025411759384395
  },
  "gate_pass": true,
  "timestamp": 1759373518.994957,
  "_slug": "github.com-danielgonzagat-aequitas"
}