{
  "fusion": "github.com-danielgonzagat-typia",
  "plan": {
    "source_url": "https://github.com/danielgonzagat/typia",
    "mode": "auto"
  },
  "genes": {
    "source_url": "https://github.com/danielgonzagat/typia",
    "reachable": true
  },
  "adapter": {
    "engine": "NeuroEvoHybrid",
    "population": 8,
    "generations": 1,
    "model": "distilbert-base-uncased"
  },
  "metrics": {
    "caos_pre": 0.7975835740559978,
    "caos_pos": 0.8129138996871913,
    "delta_linf": 0.0032398817356966737,
    "sr": 0.8652716087595563,
    "G": 0.8661985150852142,
    "ece": 0.011356849846518793,
    "rho_bias": 1.0131541609884145,
    "fp": 0.02302906535153145
  },
  "gate_pass": true,
  "timestamp": 1759384023.191923,
  "_slug": "github.com-danielgonzagat-typia"
}