{
  "fusion": "github.com-danielgonzagat-streamlit",
  "plan": {
    "source_url": "https://github.com/danielgonzagat/streamlit",
    "mode": "auto"
  },
  "genes": {
    "source_url": "https://github.com/danielgonzagat/streamlit",
    "reachable": true
  },
  "adapter": {
    "engine": "NeuroEvoHybrid",
    "population": 8,
    "generations": 1,
    "model": "distilbert-base-uncased"
  },
  "metrics": {
    "caos_pre": 0.7975835740559978,
    "caos_pos": 0.8128654290277123,
    "delta_linf": 0.0032421533764187688,
    "sr": 0.8656567877952737,
    "G": 0.8660236461695093,
    "ece": 0.011350733421183166,
    "rho_bias": 1.0130765514016085,
    "fp": 0.023030745464976847
  },
  "gate_pass": true,
  "timestamp": 1759387615.271904,
  "_slug": "github.com-danielgonzagat-streamlit"
}