{
  "fusion": "github.com-danielgonzagat-tldraw",
  "plan": {
    "source_url": "https://github.com/danielgonzagat/tldraw",
    "mode": "auto"
  },
  "genes": {
    "source_url": "https://github.com/danielgonzagat/tldraw",
    "reachable": true
  },
  "adapter": {
    "engine": "NeuroEvoHybrid",
    "population": 8,
    "generations": 1,
    "model": "distilbert-base-uncased"
  },
  "metrics": {
    "caos_pre": 0.7975835740559978,
    "caos_pos": 0.8130901822660674,
    "delta_linf": 0.003239487241153347,
    "sr": 0.8656748643189561,
    "G": 0.8658321460288021,
    "ece": 0.011356609738839177,
    "rho_bias": 1.0130030002831407,
    "fp": 0.0230349648004225
  },
  "gate_pass": true,
  "timestamp": 1759358573.4102552,
  "_slug": "github.com-danielgonzagat-tldraw"
}