{
  "fusion": "github.com-danielgonzagat-deepfacelab",
  "plan": {
    "source_url": "https://github.com/danielgonzagat/DeepFaceLab",
    "mode": "auto"
  },
  "genes": {
    "source_url": "https://github.com/danielgonzagat/DeepFaceLab",
    "reachable": true
  },
  "adapter": {
    "engine": "NeuroEvoHybrid",
    "population": 8,
    "generations": 1,
    "model": "distilbert-base-uncased"
  },
  "metrics": {
    "caos_pre": 0.7975835740559978,
    "caos_pos": 0.8131322728477616,
    "delta_linf": 0.0032396254470337528,
    "sr": 0.8650968822294954,
    "G": 0.8657375085733975,
    "ece": 0.01135054220419499,
    "rho_bias": 1.0133810513981016,
    "fp": 0.02302909162645808
  },
  "gate_pass": true,
  "timestamp": 1759395223.5043032,
  "_slug": "github.com-danielgonzagat-deepfacelab"
}