{
  "fusion": "github.com-danielgonzagat-penin-monorepo",
  "plan": {
    "source_url": "https://github.com/danielgonzagat/penin-monorepo",
    "mode": "auto"
  },
  "genes": {
    "source_url": "https://github.com/danielgonzagat/penin-monorepo",
    "reachable": true
  },
  "adapter": {
    "engine": "NeuroEvoHybrid",
    "population": 8,
    "generations": 1,
    "model": "distilbert-base-uncased"
  },
  "metrics": {
    "caos_pre": 0.7975835740559978,
    "caos_pos": 0.8131474181200927,
    "delta_linf": 0.0032419220719788477,
    "sr": 0.8649240605593421,
    "G": 0.8657189999299253,
    "ece": 0.011356620479086482,
    "rho_bias": 1.0133035389037393,
    "fp": 0.023030091789096083
  },
  "gate_pass": true,
  "timestamp": 1759382992.071386,
  "_slug": "github.com-danielgonzagat-penin-monorepo"
}