{
  "fusion": "github.com-danielgonzagat-did-verification-consensus-protocol",
  "plan": {
    "source_url": "https://github.com/danielgonzagat/did-verification-consensus-protocol",
    "mode": "auto"
  },
  "genes": {
    "source_url": "https://github.com/danielgonzagat/did-verification-consensus-protocol",
    "reachable": true
  },
  "adapter": {
    "engine": "NeuroEvoHybrid",
    "population": 8,
    "generations": 1,
    "model": "distilbert-base-uncased"
  },
  "metrics": {
    "caos_pre": 0.7975835740559978,
    "caos_pos": 0.8131219097257973,
    "delta_linf": 0.003241862964264543,
    "sr": 0.8651009291055941,
    "G": 0.8656696333621567,
    "ece": 0.011357131236045669,
    "rho_bias": 1.0132585252291944,
    "fp": 0.023021866234339255
  },
  "gate_pass": true,
  "timestamp": 1759371531.591082,
  "_slug": "github.com-danielgonzagat-did-verification-consensus-protocol"
}