{
  "fusion": "github.com-danielgonzagat-zenml",
  "plan": {
    "source_url": "https://github.com/danielgonzagat/zenml",
    "mode": "auto"
  },
  "genes": {
    "source_url": "https://github.com/danielgonzagat/zenml",
    "reachable": true
  },
  "adapter": {
    "engine": "NeuroEvoHybrid",
    "population": 8,
    "generations": 1,
    "model": "distilbert-base-uncased"
  },
  "metrics": {
    "caos_pre": 0.7975835740559978,
    "caos_pos": 0.8130034749009288,
    "delta_linf": 0.0032411347041689004,
    "sr": 0.8653813861228903,
    "G": 0.8664959846428215,
    "ece": 0.011357433443823192,
    "rho_bias": 1.0132324318888413,
    "fp": 0.023034996426340226
  },
  "gate_pass": true,
  "timestamp": 1759374903.207377,
  "_slug": "github.com-danielgonzagat-zenml"
}