{
  "fusion": "github.com-danielgonzagat-deepfacelab",
  "plan": {
    "source_url": "https://github.com/danielgonzagat/DeepFaceLab",
    "mode": "auto"
  },
  "genes": {
    "source_url": "https://github.com/danielgonzagat/DeepFaceLab",
    "reachable": true
  },
  "adapter": {
    "engine": "NeuroEvoHybrid",
    "population": 8,
    "generations": 1,
    "model": "distilbert-base-uncased"
  },
  "metrics": {
    "caos_pre": 0.7975835740559978,
    "caos_pos": 0.8131458519772323,
    "delta_linf": 0.0032414774808000343,
    "sr": 0.8651206881975245,
    "G": 0.8662459312485749,
    "ece": 0.011348267918802394,
    "rho_bias": 1.013225500847953,
    "fp": 0.023028495707062755
  },
  "gate_pass": true,
  "timestamp": 1759376250.4555478,
  "_slug": "github.com-danielgonzagat-deepfacelab"
}