{
  "fusion": "github.com-danielgonzagat-megaiaaa",
  "plan": {
    "source_url": "https://github.com/danielgonzagat/megaIAAA",
    "mode": "auto"
  },
  "genes": {
    "source_url": "https://github.com/danielgonzagat/megaIAAA",
    "reachable": true
  },
  "adapter": {
    "engine": "NeuroEvoHybrid",
    "population": 8,
    "generations": 1,
    "model": "distilbert-base-uncased"
  },
  "metrics": {
    "caos_pre": 0.7975835740559978,
    "caos_pos": 0.8128211117036077,
    "delta_linf": 0.0032403747600061343,
    "sr": 0.8649726442017129,
    "G": 0.8663169741039983,
    "ece": 0.011355541808792998,
    "rho_bias": 1.0137369634764688,
    "fp": 0.023025347111694815
  },
  "gate_pass": true,
  "timestamp": 1759395990.7186282,
  "_slug": "github.com-danielgonzagat-megaiaaa"
}