{
  "fusion": "github.com-danielgonzagat-did-verification-consensus-protocol",
  "plan": {
    "source_url": "https://github.com/danielgonzagat/did-verification-consensus-protocol",
    "mode": "auto"
  },
  "genes": {
    "source_url": "https://github.com/danielgonzagat/did-verification-consensus-protocol",
    "reachable": true
  },
  "adapter": {
    "engine": "NeuroEvoHybrid",
    "population": 8,
    "generations": 1,
    "model": "distilbert-base-uncased"
  },
  "metrics": {
    "caos_pre": 0.7975835740559978,
    "caos_pos": 0.8129577071832957,
    "delta_linf": 0.003241738392124615,
    "sr": 0.8655196215379016,
    "G": 0.8657977488327552,
    "ece": 0.011353327724092546,
    "rho_bias": 1.0135443984523935,
    "fp": 0.023037342637473982
  },
  "gate_pass": true,
  "timestamp": 1759361798.232661,
  "_slug": "github.com-danielgonzagat-did-verification-consensus-protocol"
}