{
  "fusion": "github.com-danielgonzagat-penin-monorepo",
  "plan": {
    "source_url": "https://github.com/danielgonzagat/penin-monorepo",
    "mode": "auto"
  },
  "genes": {
    "source_url": "https://github.com/danielgonzagat/penin-monorepo",
    "reachable": true
  },
  "adapter": {
    "engine": "NeuroEvoHybrid",
    "population": 8,
    "generations": 1,
    "model": "distilbert-base-uncased"
  },
  "metrics": {
    "caos_pre": 0.7975835740559978,
    "caos_pos": 0.8128311047438528,
    "delta_linf": 0.0032409292975251855,
    "sr": 0.8650307308701135,
    "G": 0.8657828843576543,
    "ece": 0.011349537203094605,
    "rho_bias": 1.0130744186982024,
    "fp": 0.023031664570095672
  },
  "gate_pass": true,
  "timestamp": 1759364714.6693141,
  "_slug": "github.com-danielgonzagat-penin-monorepo"
}