{
  "fusion": "github.com-danielgonzagat-opencv",
  "plan": {
    "source_url": "https://github.com/danielgonzagat/opencv",
    "mode": "auto"
  },
  "genes": {
    "source_url": "https://github.com/danielgonzagat/opencv",
    "reachable": true
  },
  "adapter": {
    "engine": "NeuroEvoHybrid",
    "population": 8,
    "generations": 1,
    "model": "distilbert-base-uncased"
  },
  "metrics": {
    "caos_pre": 0.7975835740559978,
    "caos_pos": 0.813160677926308,
    "delta_linf": 0.0032399989323235972,
    "sr": 0.8649186705439907,
    "G": 0.865796273507985,
    "ece": 0.011347441298594975,
    "rho_bias": 1.0129564861550027,
    "fp": 0.023021336510654404
  },
  "gate_pass": true,
  "timestamp": 1759381657.930942,
  "_slug": "github.com-danielgonzagat-opencv"
}